COPYING
MANIFEST.in
README.rst
setup.py
zanata2fedmsg.py
utility/zanata2fedmsg-webhook-generator.py
zanata2fedmsg.egg-info/PKG-INFO
zanata2fedmsg.egg-info/SOURCES.txt
zanata2fedmsg.egg-info/dependency_links.txt
zanata2fedmsg.egg-info/requires.txt
zanata2fedmsg.egg-info/top_level.txt