Metadata-Version: 1.0
Name: zanata2fedmsg
Version: 0.2
Summary: zanata2fedmsg bridges zanata to fedmsg
Home-page: https://github.com/fedora-infra/zanata2fedmsg
Author: Ralph Bean
Author-email: rbean@redhat.com
License: GPLv3+
Platform: UNKNOWN
